fcg/__init__.py
fcg/generator.py
fcg/version.py
fcg-1.2.0.dist-info/LICENSE
fcg-1.2.0.dist-info/METADATA
fcg-1.2.0.dist-info/WHEEL
fcg-1.2.0.dist-info/entry_points.txt
fcg-1.2.0.dist-info/top_level.txt
fcg-1.2.0.dist-info/zip-safe
fcg-1.2.0.dist-info/RECORD
