Metadata-Version: 2.1
Name: fcg
Version: 1.2.0
Summary: fastapi code generator
Home-page: https://github.com/mzrwalzy/fcg.git
Author: charon.
Author-email: mzrwalzy@163.com
License: UNKNOWN
Platform: UNKNOWN
Classifier: Programming Language :: Python :: 3
Classifier: License :: OSI Approved :: MIT License
Classifier: Operating System :: OS Independent
License-File: LICENSE
Requires-Dist: click (==8.0.1)
